{
  "_class": "group",
  "booleanOperation": -1,
  "clippingMaskMode": 0,
  "do_objectID": "3FABCF9B-3C0E-4FC8-B609-9B5BE0799B37",
  "exportOptions": {
    "_class": "exportOptions",
    "exportFormats": [
    ],
    "includedLayerIds": [
    ],
    "layerOptions": 0,
    "shouldTrim": false
  },
  "frame": {
    "_class": "rect",
    "constrainProportions": false,
    "height": 249,
    "width": 14,
    "x": 537,
    "y": 451
  },
  "groupLayout": {
    "_class": "MSImmutableFreeformGroupLayout"
  },
  "hasClickThrough": false,
  "hasClippingMask": false,
  "isFixedToViewport": false,
  "isFlippedHorizontal": false,
  "isFlippedVertical": false,
  "isLocked": false,
  "isVisible": true,
  "layerListExpandedType": 0,
  "layers": [
    {
      "class": "text",
      "id": "B02293D4-34AA-44C7-85E3-533924A11F9E"
    },
    {
      "class": "shapePath",
      "id": "A56A256B-2261-4727-ACAB-C2CF5A9DE4BC"
    }
  ],
  "maintainScrollPosition": false,
  "name": "btn_scroll",
  "nameIsFixed": true,
  "resizingConstraint": 44,
  "resizingType": 0,
  "rotation": 0,
  "shouldBreakMaskChain": false,
  "style": {
    "_class": "style",
    "blur": {
      "_class": "blur",
      "center": "{0.5, 0.5}",
      "isEnabled": false,
      "motionAngle": 0,
      "radius": 10,
      "saturation": 1,
      "type": 0
    },
    "borderOptions": {
      "_class": "borderOptions",
      "dashPattern": [
      ],
      "isEnabled": true,
      "lineCapStyle": 0,
      "lineJoinStyle": 0
    },
    "borders": [
    ],
    "colorControls": {
      "_class": "colorControls",
      "brightness": 0,
      "contrast": 1,
      "hue": 0,
      "isEnabled": false,
      "saturation": 1
    },
    "contextSettings": {
      "_class": "graphicsContextSettings",
      "blendMode": 0,
      "opacity": 1
    },
    "do_objectID": "6D3BD6D6-AD8C-4F00-AD9A-744005E1AC8F",
    "endMarkerType": 0,
    "fills": [
    ],
    "innerShadows": [
    ],
    "miterLimit": 10,
    "shadows": [
    ],
    "startMarkerType": 0,
    "windingRule": 1
  },
  "userInfo": {
    "com.animaapp.stc-sketch-plugin": {
      "kModelPropertiesKey": {
        "constraints": {
          "automatic": 1,
          "modelID": "viewConstraints_2e027cdd-64f1-4d35-85b2-c4837d526501",
          "model_class": "ADModelViewConstraints",
          "model_version": 0,
          "right": {
            "constant": 52,
            "enabled": 1,
            "modelID": "constraint_30d7b3bd-b2ea-45af-9e2a-badeb500a3e7",
            "model_class": "ADModelConstraint",
            "model_version": 0,
            "multiplier": 0
          },
          "scaleFactor": 1
        }
      }
    }
  }
}